goolabs/__init__.py
goolabs/client.py
goolabs/commands.py
goolabs-0.4.0.dist-info/DESCRIPTION.rst
goolabs-0.4.0.dist-info/METADATA
goolabs-0.4.0.dist-info/RECORD
goolabs-0.4.0.dist-info/WHEEL
goolabs-0.4.0.dist-info/entry_points.txt
goolabs-0.4.0.dist-info/metadata.json
goolabs-0.4.0.dist-info/top_level.txt
